pybbda/__init__.py
pybbda/analysis/__init__.py
pybbda/analysis/utils.py
pybbda/analysis/projections/__init__.py
pybbda/analysis/projections/marcels/__init__.py
pybbda/analysis/projections/marcels/age_adjustment.py
pybbda/analysis/projections/marcels/marcels_base.py
pybbda/analysis/projections/marcels/marcels_batting.py
pybbda/analysis/projections/marcels/marcels_pitching.py
pybbda/analysis/run_expectancy/__init__.py
pybbda/analysis/run_expectancy/markov/__init__.py
pybbda/analysis/run_expectancy/markov/cli.py
pybbda/analysis/run_expectancy/markov/markov.py
pybbda/analysis/simulations/__init__.py
pybbda/analysis/simulations/constants.py
pybbda/analysis/simulations/components/__init__.py
pybbda/analysis/simulations/components/event.py
pybbda/analysis/simulations/components/lineup.py
pybbda/analysis/simulations/components/player.py
pybbda/analysis/simulations/components/player_registry.py
pybbda/analysis/simulations/components/state.py
pybbda/analysis/trajectories/__init__.py
pybbda/analysis/trajectories/batted_balls/__init__.py
pybbda/analysis/trajectories/batted_balls/calculator.py
pybbda/analysis/trajectories/batted_balls/parameters.py
pybbda/data/__init__.py
pybbda/data/sources/__init__.py
pybbda/data/sources/baseball_reference/__init__.py
pybbda/data/sources/baseball_reference/_update.py
pybbda/data/sources/baseball_reference/data.py
pybbda/data/sources/data_source/__init__.py
pybbda/data/sources/data_source/base.py
pybbda/data/sources/fangraphs/__init__.py
pybbda/data/sources/fangraphs/_update.py
pybbda/data/sources/fangraphs/constants.py
pybbda/data/sources/fangraphs/data.py
pybbda/data/sources/lahman/__init__.py
pybbda/data/sources/lahman/_update.py
pybbda/data/sources/lahman/data.py
pybbda/data/sources/retrosheet/__init__.py
pybbda/data/sources/retrosheet/_update.py
pybbda/data/sources/retrosheet/data.py
pybbda/data/sources/statcast/__init__.py
pybbda/data/sources/statcast/_update.py
pybbda/data/sources/statcast/constants.py
pybbda-0.4.3.dist-info/LICENSE
pybbda-0.4.3.dist-info/METADATA
pybbda-0.4.3.dist-info/WHEEL
pybbda-0.4.3.dist-info/entry_points.txt
pybbda-0.4.3.dist-info/top_level.txt
pybbda-0.4.3.dist-info/RECORD
