Metadata-Version: 2.1
Name: pybbda
Version: 0.4.3
Summary: Baseball data and analysis in Python
Home-page: https://github.com/bdilday/pybbda
Author: Ben Dilday
Author-email: ben.dilday.phd@gmail.com
Classifier: Programming Language :: Python :: 3
Classifier: License :: OSI Approved :: GNU General Public License v2 (GPLv2)
Classifier: Operating System :: OS Independent
License-File: LICENSE
Requires-Dist: attrs
Requires-Dist: beautifulsoup4
Requires-Dist: lxml
Requires-Dist: pandas
Requires-Dist: requests
Requires-Dist: scipy
Requires-Dist: sqlalchemy
Requires-Dist: tqdm
Requires-Dist: pychadwick
Requires-Dist: matplotlib
Requires-Dist: seaborn
Requires-Dist: plotnine
Requires-Dist: adjustText
Requires-Dist: namedframes
